pyre_check/__init__.py
pyre_check/client/__init__.py
pyre_check/client/backend_arguments.py
pyre_check/client/background_tasks.py
pyre_check/client/command_arguments.py
pyre_check/client/coverage_data.py
pyre_check/client/daemon_socket.py
pyre_check/client/dataclasses_json_extensions.py
pyre_check/client/dataclasses_merge.py
pyre_check/client/error.py
pyre_check/client/filesystem.py
pyre_check/client/find_directories.py
pyre_check/client/frontend_configuration.py
pyre_check/client/identifiers.py
pyre_check/client/json_rpc.py
pyre_check/client/log_lsp_event.py
pyre_check/client/pyre.py
pyre_check/client/remote_logger.py
pyre_check/client/terminal.py
pyre_check/client/timer.py
pyre_check/client/version.py
pyre_check/client/commands/__init__.py
pyre_check/client/commands/analyze.py
pyre_check/client/commands/check.py
pyre_check/client/commands/commands.py
pyre_check/client/commands/daemon_querier.py
pyre_check/client/commands/daemon_query.py
pyre_check/client/commands/error_code_to_link_mapper.py
pyre_check/client/commands/expression_level_coverage.py
pyre_check/client/commands/incremental.py
pyre_check/client/commands/infer.py
pyre_check/client/commands/info.py
pyre_check/client/commands/initialization.py
pyre_check/client/commands/initialize.py
pyre_check/client/commands/initialize_pysa.py
pyre_check/client/commands/kill.py
pyre_check/client/commands/launch_and_subscribe_handler.py
pyre_check/client/commands/libcst_util.py
pyre_check/client/commands/no_daemon_query.py
pyre_check/client/commands/persistent.py
pyre_check/client/commands/profile.py
pyre_check/client/commands/pyre_language_server.py
pyre_check/client/commands/pyre_server_options.py
pyre_check/client/commands/pysa_server.py
pyre_check/client/commands/query.py
pyre_check/client/commands/query_response.py
pyre_check/client/commands/rage.py
pyre_check/client/commands/report.py
pyre_check/client/commands/report_any_expressions.py
pyre_check/client/commands/restart.py
pyre_check_nightly-0.0.101757589089.dist-info/LICENSE
pyre_check_nightly-0.0.101757589089.dist-info/METADATA
pyre_check_nightly-0.0.101757589089.dist-info/WHEEL
pyre_check_nightly-0.0.101757589089.dist-info/entry_points.txt
pyre_check_nightly-0.0.101757589089.dist-info/top_level.txt
pyre_check_nightly-0.0.101757589089.dist-info/RECORD
