Metadata-Version: 2.1
Name: pyre-check-nightly
Version: 0.0.101757589089
Summary: A performant type checker for Python
Home-page: https://pyre-check.org/
Download-URL: https://github.com/facebook/pyre-check
Author: Facebook
Author-email: pyre@fb.com
Maintainer: Facebook
Maintainer-email: pyre@fb.com
License: MIT
Keywords: typechecker development
Classifier: Development Status :: 5 - Production/Stable
Classifier: Environment :: Console
Classifier: Intended Audience :: Developers
Classifier: License :: OSI Approved :: MIT License
Classifier: Operating System :: MacOS
Classifier: Operating System :: POSIX :: Linux
Classifier: Programming Language :: Python
Classifier: Programming Language :: Python :: 3
Classifier: Programming Language :: Python :: 3.8
Classifier: Programming Language :: Python :: 3.9
Classifier: Programming Language :: Python :: 3.10
Classifier: Programming Language :: Python :: 3.11
Classifier: Programming Language :: Python :: 3.12
Classifier: Topic :: Software Development
Classifier: Typing :: Typed
Requires-Python: >=3.8
License-File: LICENSE
Requires-Dist: click (<8.2.0,>=8.0)
Requires-Dist: dataclasses-json (==0.5.7)
Requires-Dist: libcst
Requires-Dist: psutil
Requires-Dist: pyre-extensions (>=0.0.29)
Requires-Dist: tabulate
Requires-Dist: testslide (>=2.7.0)
Requires-Dist: typing-extensions
Requires-Dist: typing-inspect
Requires-Dist: tomli
Requires-Dist: tomli-w
